dac7/__init__.py
dac7/constants.py
dac7/core.py
dac7/encryption.py
dac7/main.py
dac7/models/__init__.py
dac7/models/dpi.py
dac7/models/enums.py
dac7/models/flat.py
dac7/naming.py
dac7/py.typed
dac7/schemas/DPIXML_v1.1-fr1.xsd
dac7/schemas/isodpitypes_v1.0-fr1.xsd
dac7/schemas/oecddpitypes_v1.0-fr1.xsd
dac7-2024.4.1.dist-info/LICENSE.md
dac7-2024.4.1.dist-info/METADATA
dac7-2024.4.1.dist-info/WHEEL
dac7-2024.4.1.dist-info/entry_points.txt
dac7-2024.4.1.dist-info/RECORD
