Metadata-Version: 2.1
Name: dac7
Version: 2024.4.1
Summary: Tooling for DAC7
License: LICENSE.md
Author: Nicolas Bonnotte
Author-email: nicolas.bonnotte@backmarket.com
Requires-Python: >=3.11,<3.14
Classifier: License :: Other/Proprietary License
Classifier: Programming Language :: Python :: 3
Classifier: Programming Language :: Python :: 3.11
Classifier: Programming Language :: Python :: 3.12
Classifier: Programming Language :: Python :: 3.13
Requires-Dist: annotated-types (>=0.7.0,<0.8.0)
Requires-Dist: pydantic (>=2.5.2,<3.0.0)
Requires-Dist: python-gnupg (>=0.5.2,<0.6.0)
Requires-Dist: requests (>=2.31.0,<3.0.0)
Requires-Dist: typer (>=0.15.0,<0.16.0)
Requires-Dist: xmlschema (>=3.0.0,<4.0.0)
